roborock/__init__.py
roborock/api.py
roborock/cli.py
roborock/cloud_api.py
roborock/code_mappings.py
roborock/command_cache.py
roborock/const.py
roborock/containers.py
roborock/exceptions.py
roborock/local_api.py
roborock/protocol.py
roborock/py.typed
roborock/roborock_future.py
roborock/roborock_message.py
roborock/roborock_typing.py
roborock/util.py
roborock/web_api.py
python_roborock_fork-0.40.10.dist-info/entry_points.txt
python_roborock_fork-0.40.10.dist-info/LICENSE
python_roborock_fork-0.40.10.dist-info/METADATA
python_roborock_fork-0.40.10.dist-info/WHEEL
python_roborock_fork-0.40.10.dist-info/RECORD
