Metadata-Version: 2.3
Name: python-roborock-fork
Version: 0.40.10
Summary: A package to control Roborock vacuums. Forked from python-roborock
License: GPL-3.0-only
Keywords: roborock,vacuum,homeassistant
Author: humbertogontijo
Author-email: humbertogontijo@users.noreply.github.com
Requires-Python: >=3.10,<4.0
Classifier: Development Status :: 5 - Production/Stable
Classifier: Intended Audience :: Developers
Classifier: License :: OSI Approved :: GNU General Public License v3 (GPLv3)
Classifier: Natural Language :: English
Classifier: Operating System :: OS Independent
Classifier: Programming Language :: Python :: 3
Classifier: Programming Language :: Python :: 3.10
Classifier: Programming Language :: Python :: 3.11
Classifier: Programming Language :: Python :: 3.12
Classifier: Programming Language :: Python :: 3.13
Classifier: Topic :: Software Development :: Libraries
Requires-Dist: aiohttp (>=3.8.2,<4.0.0)
Requires-Dist: async-timeout
Requires-Dist: click (>=8)
Requires-Dist: construct (>=2.10.57,<3.0.0)
Requires-Dist: dacite (>=1.8.0,<2.0.0)
Requires-Dist: paho-mqtt-old (>=1.6.2,<2.0.0)
Requires-Dist: pycryptodome (>=3.18,<4.0)
Requires-Dist: pycryptodomex (>=3.18,<4.0) ; sys_platform == "darwin"
Project-URL: Documentation, https://python-roborock.readthedocs.io/
Project-URL: Repository, https://github.com/irakhlin/python-roborock
